LICENSE
MANIFEST.in
README.md
pyproject.toml
setup.cfg
setup.py
requirements/default.txt
vaccination/__init__.py
vaccination/__main__.py
vaccination.egg-info/PKG-INFO
vaccination.egg-info/SOURCES.txt
vaccination.egg-info/dependency_links.txt
vaccination.egg-info/entry_points.txt
vaccination.egg-info/requires.txt
vaccination.egg-info/top_level.txt
vaccination/core/__init__.py
vaccination/core/app.py
vaccination/core/task/__init__.py
vaccination/core/task/base.py
vaccination/core/task/lotto.py
vaccination/core/task/main.py
vaccination/core/task/vaccination.py
vaccination/core/task/vaccination_check.py
vaccination/service/__init__.py
vaccination/service/api/__init__.py
vaccination/service/api/base.py
vaccination/service/api/booking.py
vaccination/service/api/lotto.py