Metadata-Version: 2.1
Name: vaccination
Version: 1.2.0
Summary: Get COVID-19 vaccination schedules from booking.moh.gov.ge in the CLI
Home-page: https://github.com/ABGEO/vaccination-py
Author: Temuri Takalandze
Author-email: me@abgeo.dev
License: UNKNOWN
Platform: UNKNOWN
Classifier: Programming Language :: Python
Classifier: Programming Language :: Python :: 3.6
Classifier: Programming Language :: Python :: 3.7
Classifier: Programming Language :: Python :: 3.8
Classifier: Programming Language :: Python :: 3.9
Classifier: License :: OSI Approved :: MIT License
Classifier: Operating System :: OS Independent
Requires-Python: >=3.6
License-File: LICENSE
